bago/__init__.py
bago/bagoMain.py
bago/models.py
bago/rawDataHelper.py
bago-0.0.27.dist-info/METADATA
bago-0.0.27.dist-info/WHEEL
bago-0.0.27.dist-info/licenses/LICENSE
bago-0.0.27.dist-info/RECORD
