Metadata-Version: 2.1
Name: bago
Version: 0.0.27
Summary: LC gradient optimization and evaluation
Project-URL: Homepage, https://github.com/Waddlessss/BAGO
Author-email: Huaxu <yhxchem@outlook.com>
Maintainer-email: Huaxu <yhxchem@outlook.com>
License-File: LICENSE
Classifier: License :: OSI Approved :: MIT License
Classifier: Operating System :: OS Independent
Classifier: Programming Language :: Python :: 3
Requires-Python: >=3.8
Requires-Dist: numpy>=1.19.5
Requires-Dist: pandas>=1.2.4
Requires-Dist: scikit-learn>=1.0.2
Requires-Dist: scipy>=1.7.1
